superset_iris/__init__.py
superset_iris/engine.py
superset_iris-0.4.0.dist-info/LICENSE
superset_iris-0.4.0.dist-info/METADATA
superset_iris-0.4.0.dist-info/WHEEL
superset_iris-0.4.0.dist-info/entry_points.txt
superset_iris-0.4.0.dist-info/top_level.txt
superset_iris-0.4.0.dist-info/RECORD
