Metadata-Version: 2.1
Name: superset-iris
Version: 0.4.0
Summary: InterSystems IRIS Engine for Apache Superset
Home-page: https://github.com/caretdev/superset-iris
Maintainer: CaretDev
Maintainer-email: dmitry@caretdev.com
License: MIT
Project-URL: Source, https://github.com/caretdev/superset-iris
Project-URL: Tracker, https://github.com/caretdev/superset-iris/issues
Keywords: "Superset InterSystems IRIS"
Classifier: Development Status :: 4 - Beta
Classifier: Intended Audience :: Developers
Classifier: License :: OSI Approved :: MIT License
Classifier: Programming Language :: Python
Classifier: Programming Language :: Python :: 3
Classifier: Programming Language :: Python :: 3.8
Classifier: Programming Language :: Python :: 3.9
Classifier: Programming Language :: Python :: 3.10
Classifier: Programming Language :: Python :: 3.11
Classifier: Topic :: Database :: Front-Ends
Classifier: Operating System :: OS Independent
License-File: LICENSE
Requires-Dist: sqlalchemy-iris ~=0.15.0
